byte_unit/__init__.py
byte_unit/byte_unit.py
byte_unit-1.0.0.dist-info/METADATA
byte_unit-1.0.0.dist-info/WHEEL
byte_unit-1.0.0.dist-info/RECORD
