Metadata-Version: 2.1
Name: byte-unit
Version: 1.0.0
Summary: 
Author: Jaya Bharath
Author-email: bharath21196@gmail.com
Requires-Python: >=3.9,<4.0
Classifier: Programming Language :: Python :: 3
Classifier: Programming Language :: Python :: 3.9
Classifier: Programming Language :: Python :: 3.10
Classifier: Programming Language :: Python :: 3.11
Classifier: Programming Language :: Python :: 3.12
